cudo_compute/__init__.py
cudo_compute/api_client.py
cudo_compute/auth_config.py
cudo_compute/configuration.py
cudo_compute/cudo_api.py
cudo_compute/rest.py
cudo_compute/api/__init__.py
cudo_compute/api/api_keys_api.py
cudo_compute/api/billing_api.py
cudo_compute/api/data_centers_api.py
cudo_compute/api/default_api.py
cudo_compute/api/disks_api.py
cudo_compute/api/machine_types_api.py
cudo_compute/api/networks_api.py
cudo_compute/api/object_storage_api.py
cudo_compute/api/permissions_api.py
cudo_compute/api/projects_api.py
cudo_compute/api/search_api.py
cudo_compute/api/ssh_keys_api.py
cudo_compute/api/user_api.py
cudo_compute/api/virtual_machines_api.py
cudo_compute/models/__init__.py
cudo_compute/models/activate_body.py
cudo_compute/models/add_billing_account_user_permission_body.py
cudo_compute/models/add_data_center_user_permission_body.py
cudo_compute/models/add_project_user_permission_body.py
cudo_compute/models/api_key.py
cudo_compute/models/attach_security_group_response.py
cudo_compute/models/attach_storage_disk_response.py
cudo_compute/models/billing_account.py
cudo_compute/models/billing_account_payment_method.py
cudo_compute/models/billing_account_payment_methods.py
cudo_compute/models/billing_account_project.py
cudo_compute/models/billing_account_result.py
cudo_compute/models/billing_account_setup_intent.py
cudo_compute/models/billing_account_spend_row.py
cudo_compute/models/billing_account_state.py
cudo_compute/models/billing_address.py
cudo_compute/models/charge.py
cudo_compute/models/cluster.py
cudo_compute/models/commitment_term.py
cudo_compute/models/connect_vm_response.py
cudo_compute/models/count_hosts_response.py
cudo_compute/models/count_vms_response.py
cudo_compute/models/cpu_topology.py
cudo_compute/models/create_billing_account_credit_payment_response.py
cudo_compute/models/create_billing_account_request.py
cudo_compute/models/create_disk_snapshot_body.py
cudo_compute/models/create_disk_snapshot_response.py
cudo_compute-0.3.5.dist-info/METADATA
cudo_compute-0.3.5.dist-info/WHEEL
cudo_compute-0.3.5.dist-info/RECORD
