Metadata-Version: 2.4
Name: cudo-compute
Version: 0.3.5
Summary: A client for cudocompute.com
Project-URL: Homepage, https://www.cudocompute.com
Project-URL: Bug Tracker, https://github.com/CudoVentures/cudo-compute-python-client/issues
Author-email: Cudo Ventures <dev@cudoventures.com>
Classifier: License :: OSI Approved :: MIT License
Classifier: Operating System :: OS Independent
Classifier: Programming Language :: Python :: 3
Requires-Python: >=3.8
Requires-Dist: certifi>=14.05.14
Requires-Dist: python-dateutil>=2.5.3
Requires-Dist: ruamel-yaml>=0.17.2
Requires-Dist: six>=1.10
Requires-Dist: urllib3>=1.15.1
